bda.calendar.base-1.2.5-nspkg.pth
bda/calendar/base/__init__.py
bda/calendar/base/calculator.py
bda/calendar/base/configure.zcml
bda/calendar/base/converter.py
bda/calendar/base/inspector.py
bda/calendar/base/interfaces.py
bda/calendar/base/recurring.py
bda/calendar/base/timezone.py
bda.calendar.base-1.2.5.dist-info/METADATA
bda.calendar.base-1.2.5.dist-info/WHEEL
bda.calendar.base-1.2.5.dist-info/namespace_packages.txt
bda.calendar.base-1.2.5.dist-info/top_level.txt
bda.calendar.base-1.2.5.dist-info/RECORD
