Metadata-Version: 2.1
Name: bda.calendar.base
Version: 1.2.5
Summary: Base common calendaring features: Convinience or not coverd yet.
Home-page: https://github.com/bluedynamics/bda.calendar.base
Author: Jens Klein, Robert Niedereiter
Author-email: dev@bluedynamics.com
License: BSD
Keywords: Calendaring
Platform: UNKNOWN
Classifier: Development Status :: 4 - Beta
Classifier: Environment :: Web Environment
Classifier: Framework :: Zope2
Classifier: License :: OSI Approved :: GNU General Public License (GPL)
Classifier: Operating System :: OS Independent
Classifier: Programming Language :: Python
Classifier: Topic :: Internet :: WWW/HTTP :: Dynamic Content
Requires-Dist: pytz
Requires-Dist: setuptools
Requires-Dist: zope.interface
